flitsr/__init__.py
flitsr/__main__.py
flitsr/args.py
flitsr/const_iter.py
flitsr/cutoff_points.py
flitsr/errors.py
flitsr/file.py
flitsr/main.py
flitsr/merge.py
flitsr/ordering_driver.py
flitsr/output.py
flitsr/percent_at_n.py
flitsr/plot.py
flitsr/precision_recall.py
flitsr/py.typed
flitsr/ranking.py
flitsr/read_ranking.py
flitsr/run_all.py
flitsr/singleton.py
flitsr/spectrum.py
flitsr/spectrumBuilder.py
flitsr/split_faults.py
flitsr/stmt_to_method.py
flitsr/suspicious.py
flitsr/tie.py
flitsr/top.py
flitsr/transform.py
flitsr/weffort.py
flitsr/advanced/__init__.py
flitsr/advanced/artemis_wrapper.py
flitsr/advanced/attributes.py
flitsr/advanced/cluster.py
flitsr/advanced/flitsr.py
flitsr/advanced/parallel-1.0-SNAPSHOT-jar-with-dependencies.jar
flitsr/advanced/parallel.py
flitsr/advanced/ranker.py
flitsr/advanced/refiner.py
flitsr/advanced/sbfl.py
flitsr/advanced/artemis_impl/__init__.py
flitsr/advanced/artemis_impl/artemis.py
flitsr/input/__init__.py
flitsr/input/gzoltar_input.py
flitsr/input/input_reader.py
flitsr/input/tcm_input.py
flitsr-2.3.0.dist-info/licenses/LICENSE
flitsr-2.3.0.dist-info/METADATA
flitsr-2.3.0.dist-info/WHEEL
flitsr-2.3.0.dist-info/entry_points.txt
flitsr-2.3.0.dist-info/top_level.txt
flitsr-2.3.0.dist-info/RECORD
