Metadata-Version: 2.4
Name: flitsr
Version: 2.3.0
Summary: An automatic fault finding/localization tool for multiple faults
Author-email: Dylan Callaghan <dcallaghan@acm.org>
License-Expression: MIT
Project-URL: Homepage, https://github.com/DCallaz/flitsr
Project-URL: Issues, https://github.com/DCallaz/flitsr/issues
Classifier: Programming Language :: Python :: 3
Classifier: Operating System :: OS Independent
Classifier: Topic :: Software Development :: Debuggers
Classifier: Intended Audience :: Developers
Requires-Python: >=3.6
License-File: LICENSE
Requires-Dist: importlib_metadata; python_version < "3.10"
Requires-Dist: argcomplete
Requires-Dist: numpy
Requires-Dist: bitarray
Requires-Dist: scipy
Provides-Extra: plot
Requires-Dist: matplotlib; extra == "plot"
Dynamic: license-file
